tap_terminusdb
