Metadata-Version: 2.1
Name: tap-terminusdb
Version: 0.1.1
Summary: Singer.io tap for extracting data from TerminusDB
Home-page: http://singer.io
Author: Cheuk
License: UNKNOWN
Platform: UNKNOWN
Classifier: Programming Language :: Python :: 3 :: Only
License-File: LICENSE
